embodi/__init__.py
embodi/builder/__init__.py
embodi/builder/builder.py
embodi/builder/converter.py
embodi/builder/modelfile.py
embodi/cli/__init__.py
embodi/cli/commands.py
embodi/cli/main.py
embodi/core/__init__.py
embodi/core/embodi_os.py
embodi/core/hal.py
embodi/core/inference.py
embodi/core/kernel.py
embodi/core/nl_processor.py
embodi/core/runtime_kernel.py
embodi/demos/__init__.py
embodi/demos/voice_simulation.py
embodi/models/__init__.py
embodi/models/huggingface.py
embodi/runtime/__init__.py
embodi/runtime/container.py
embodi/runtime/image.py
embodi/runtime/runtime.py
embodi_os-0.2.0.dist-info/licenses/LICENSE
embodi_os-0.2.0.dist-info/METADATA
embodi_os-0.2.0.dist-info/WHEEL
embodi_os-0.2.0.dist-info/entry_points.txt
embodi_os-0.2.0.dist-info/top_level.txt
embodi_os-0.2.0.dist-info/RECORD
