Metadata-Version: 2.4
Name: embodi-os
Version: 0.2.0
Summary: AI-powered operating system with natural language interface
Home-page: https://github.com/dddimcha/embodiOS
Author: EMBODIOS Contributors
Author-email: dddimcha@gmail.com
License: MIT
Project-URL: Bug Tracker, https://github.com/dddimcha/embodiOS/issues
Project-URL: Documentation, https://github.com/dddimcha/embodiOS/tree/main/docs
Project-URL: Source Code, https://github.com/dddimcha/embodiOS
Classifier: Development Status :: 3 - Alpha
Classifier: Intended Audience :: Developers
Classifier: Topic :: System :: Operating System
Classifier: License :: OSI Approved :: MIT License
Classifier: Programming Language :: Python :: 3
Classifier: Programming Language :: Python :: 3.8
Classifier: Programming Language :: Python :: 3.9
Classifier: Programming Language :: Python :: 3.10
Classifier: Programming Language :: Python :: 3.11
Requires-Python: >=3.8
Requires-Dist: PyYAML>=6.0
Requires-Dist: click>=8.0
Requires-Dist: rich>=13.0
Requires-Dist: requests>=2.28
Requires-Dist: docker>=6.0
Requires-Dist: numpy>=1.21
Requires-Dist: safetensors>=0.3
Requires-Dist: huggingface-hub>=0.16
Requires-Dist: psutil>=5.9
Requires-Dist: tqdm>=4.65
Requires-Dist: tabulate>=0.9
